xworkflows/__init__.py
xworkflows/base.py
xworkflows/compat.py
xworkflows/utils.py
xworkflows-1.1.0.dist-info/LICENSE
xworkflows-1.1.0.dist-info/METADATA
xworkflows-1.1.0.dist-info/WHEEL
xworkflows-1.1.0.dist-info/top_level.txt
xworkflows-1.1.0.dist-info/RECORD
