Metadata-Version: 2.1
Name: xworkflows
Version: 1.1.0
Summary: A library implementing workflows (or state machines) for Python projects.
Home-page: https://github.com/rbarrois/xworkflows
Author: Raphaël Barrois
Author-email: raphael.barrois_xworkflows@polytechnique.org
License: BSD
Keywords: workflow,state machine,automaton
Platform: UNKNOWN
Classifier: Development Status :: 5 - Production/Stable
Classifier: Intended Audience :: Developers
Classifier: License :: OSI Approved :: BSD License
Classifier: Topic :: Software Development :: Libraries :: Python Modules
Classifier: Operating System :: OS Independent
Classifier: Programming Language :: Python :: 2
Classifier: Programming Language :: Python :: 2.7
Classifier: Programming Language :: Python :: 3
Classifier: Programming Language :: Python :: 3.4
Classifier: Programming Language :: Python :: 3.5
Classifier: Programming Language :: Python :: 3.6
Classifier: Programming Language :: Python :: 3.7
Classifier: Programming Language :: Python :: 3.8
Classifier: Programming Language :: Python :: 3.9
Requires-Python: >=2.7
Provides-Extra: dev
Requires-Dist: check-manifest ; extra == 'dev'
Requires-Dist: flake8 ; extra == 'dev'
Requires-Dist: tox ; extra == 'dev'
Requires-Dist: zest.releaser[recommended] ; extra == 'dev'
Provides-Extra: doc
Requires-Dist: Sphinx ; extra == 'doc'
Requires-Dist: sphinx-rtd-theme ; extra == 'doc'
